COPYING
MANIFEST.in
pyproject.toml
setup.cfg
setup.py
djvu/__init__.py
djvu/common.pxi
djvu/const.py
djvu/decode.pxd
djvu/decode.pyx
djvu/sexpr.pxd
djvu/sexpr.pyx
djvulibre_python.egg-info/PKG-INFO
djvulibre_python.egg-info/SOURCES.txt
djvulibre_python.egg-info/dependency_links.txt
djvulibre_python.egg-info/requires.txt
djvulibre_python.egg-info/top_level.txt
doc/README
doc/changelog
doc/todo
doc/api/annotations.rst
doc/api/conf.py
doc/api/documents.rst
doc/api/event-model.rst
doc/api/exceptions.rst
doc/api/expressions.rst
doc/api/files.rst
doc/api/geometry.rst
doc/api/index.rst
doc/api/messages.rst
doc/api/outline.rst
doc/api/pages.rst
doc/api/text-zones.rst
examples/djvu-crop-text
examples/djvu-dump-text
examples/djvu2png
private/check-for-updates
private/check-rst
tests/__init__.py
tests/sexpr-gc.py
tests/test_const.py
tests/test_decode.py
tests/test_sexpr.py
tests/tools.py
tests/examples/__init__.py
tests/examples/test_djvu2png.py
tests/examples/test_djvu_crop_text.py
tests/examples/test_djvu_dump_text.py
tests/images/Makefile
tests/images/test0.djvu
tests/images/test0.tex
tests/images/test0_crop-text.txt
tests/images/test0_dump-text.txt
tests/images/test1.djvu
tests/images/test1_foreground.png
tests/images/test1_mask.png